cavelink/__init__.py
cavelink/cavelink.py
cavelink-1.1.2.dist-info/LICENSE
cavelink-1.1.2.dist-info/METADATA
cavelink-1.1.2.dist-info/WHEEL
cavelink-1.1.2.dist-info/top_level.txt
cavelink-1.1.2.dist-info/RECORD
