Metadata-Version: 2.1
Name: cavelink
Version: 1.1.2
Summary: Fetch Cavelink data by parsing the webpage of sensors.
Home-page: https://github.com/explo-fees/cavelink
Author: Sébastien Pittet
Author-email: sebastien@pittet.org
License: MIT
Keywords: speleo cave sensor
Platform: any
Classifier: Programming Language :: Python :: 3
Classifier: Programming Language :: Python :: 3.7
Classifier: Programming Language :: Python :: 3.6
Classifier: Programming Language :: Python :: 3.5
Classifier: Programming Language :: Python :: 3.4
Classifier: Programming Language :: Python :: 2.7
Classifier: Programming Language :: Python :: 2
Classifier: License :: OSI Approved :: MIT License
Classifier: Operating System :: OS Independent
Classifier: Development Status :: 5 - Production/Stable
Classifier: Intended Audience :: Developers
Classifier: Intended Audience :: Other Audience
Requires-Dist: python-dateutil
Requires-Dist: requests
